src/clock_sar.v
module clock_sar 
#( parameter N = 8)
 (
    input wire clk_in,
    input wire clk_sample,    // Input clock (2 MHz)
    input wire rst_n,     // Active low reset
    output reg clk_out    // Output divided clock (200 kHz)
 );

    localparam IDLE = 1'b0;
    localparam START = 1'b1;

    reg current_state;
    reg [$clog2(N)-1:0] counter = 0;

    reg clk_buffer;

    always @(negedge clk_in) begin
        if (!rst_n) begin
            counter <= 0;
            clk_out <= 0;
            current_state <= IDLE;
        end 
        else begin
            case(current_state) 
                IDLE: begin
                    if(clk_sample) current_state <= START;
                end
                START: begin
                    if(counter == N-1) current_state <= IDLE;
                    counter <= counter + 1;
                end
            endcase
        end
    end

    always @(*) begin
        if(current_state == IDLE) begin
            clk_out <= 0;
        end
        else begin
            clk_out =~clk_in;
        end
    end

endmodule

src/clock_sample.v
module clock_sample
#(
    parameter N = 10 // Divide the clock by 10
)
(
    input wire clk_in,    // Input clock (2 MHz)
    input wire rst_n,     // Active low reset
    output reg clk_out    // Output divided clock (200 kHz)
);

    reg [$clog2(N)-1:0] counter = 0;

    always @(posedge clk_in) begin
        if (!rst_n) begin
            counter <= 0;
            clk_out <= 0;
        end 
        else begin
            if (counter == (N-1)) begin
                counter <= 0;
            end else begin
                counter <= counter + 1;
            end
        end
    end

    always @(*) begin
        if(counter == 0) begin
            clk_out <= clk_in;
        end
        else begin
            clk_out <= 0;
        end
    end


endmodule

src/clock_gen.v
module clock_gen (
    input wire clk_in,          // 2 MHz input clock
    input wire rst_n,           // Active low reset
    output wire clk_out_sample, // 200 kHz divided clock output
    output wire clk_out_sar     // SAR operation clock
);

    // Instantiate the clock divider
    clock_sample #(
        .N(10) // Set the divide factor to 10 for 2 MHz -> 200 kHz division
    ) clock_sample_inst (
        .clk_in(clk_in),
        .rst_n(rst_n),
        .clk_out(clk_out_sample)
    );

    clock_sar #(
        .N(8) // Number Of beats for sar bits
    ) clock_sar_inst (
        .clk_in(clk_in),
        .clk_sample(clk_out_sample),
        .rst_n(rst_n),
        .clk_out(clk_out_sar)
    );

endmodule

test/clock_test/clock_gen_tb.sv
module clock_gen_tb;

    // Inputs
    reg clk_in;
    reg rst_n;

    // Outputs
    wire clk_out_sample;
    wire clk_out_sar ;
    // Instantiate the main block (which contains the clock divider as a subblock)
    
    clock_gen uut (
        .clk_in(clk_in),
        .rst_n(rst_n),
        .clk_out_sample(clk_out_sample),
        .clk_out_sar(clk_out_sar)
    );

    // Clock generation (2 MHz, 500ns period)
    initial begin
        clk_in = 0;
        forever #250 clk_in = ~clk_in;  // Toggle clock every 250ns -> 2 MHz clock
    end

    // Test stimulus
    initial begin
        // Initialize inputs
        rst_n = 0;   // Start with reset active
        #1000;       // Wait for 1000ns (1 µs)

        rst_n = 1;   // Deassert reset
        #100000;      // Run simulation for 10 µs

        // End simulation
        $stop;
    end

    initial begin
        // Initialize VCD dump
        $dumpfile("test/clock_test/clock_gen.vcd");
        $dumpvars(0, clock_gen_tb);
    end
endmodule

test/clock_test/clock_gen.vcd
$date
	Tue Sep 24 10:36:39 2024
$end
$version
	Icarus Verilog
$end
$timescale
	1s
$end
$scope module clock_gen_tb $end
$var wire 1 ! clk_out_sar $end
$var wire 1 " clk_out_sample $end
$var reg 1 # clk_in $end
$var reg 1 $ rst_n $end
$scope module uut $end
$var wire 1 # clk_in $end
$var wire 1 $ rst_n $end
$var wire 1 ! clk_out_sar $end
$var wire 1 " clk_out_sample $end
$scope module clock_sample_inst $end
$var wire 1 # clk_in $end
$var wire 1 $ rst_n $end
$var reg 1 " clk_out $end
$var reg 4 % counter [3:0] $end
$upscope $end
$scope module clock_sar_inst $end
$var wire 1 # clk_in $end
$var wire 1 " clk_sample $end
$var wire 1 $ rst_n $end
$var reg 1 ! clk_out $end
$var reg 3 & counter [2:0] $end
$var reg 1 ' current_state $end
$upscope $end
$upscope $end
$upscope $end
$enddefinitions $end
#0
$dumpvars
0'
b0 &
b0 %
0$
0#
0"
0!
$end
#250
1"
1#
#500
0"
0#
#750
1"
1#
#1000
1!
0"
1'
0#
1$
#1250
0"
b1 %
0!
1#
#1500
b1 &
1!
0#
#1750
b10 %
0!
1#
#2000
b10 &
1!
0#
#2250
b11 %
0!
1#
#2500
b11 &
1!
0#
#2750
b100 %
0!
1#
#3000
b100 &
1!
0#
#3250
b101 %
0!
1#
#3500
b101 &
1!
0#
#3750
b110 %
0!
1#
#4000
b110 &
1!
0#
#4250
b111 %
0!
1#
#4500
b111 &
1!
0#
#4750
b1000 %
0!
1#
#5000
b0 &
0'
0!
0#
#5250
b1001 %
1#
#5500
0#
#5750
1"
b0 %
1#
#6000
1!
0"
1'
0#
#6250
0"
b1 %
0!
1#
#6500
b1 &
1!
0#
#6750
b10 %
0!
1#
#7000
b10 &
1!
0#
#7250
b11 %
0!
1#
#7500
b11 &
1!
0#
#7750
b100 %
0!
1#
#8000
b100 &
1!
0#
#8250
b101 %
0!
1#
#8500
b101 &
1!
0#
#8750
b110 %
0!
1#
#9000
b110 &
1!
0#
#9250
b111 %
0!
1#
#9500
b111 &
1!
0#
#9750
b1000 %
0!
1#
#10000
b0 &
0'
0!
0#
#10250
b1001 %
1#
#10500
0#
#10750
1"
b0 %
1#
#11000
1!
0"
1'
0#
#11250
0"
b1 %
0!
1#
#11500
b1 &
1!
0#
#11750
b10 %
0!
1#
#12000
b10 &
1!
0#
#12250
b11 %
0!
1#
#12500
b11 &
1!
0#
#12750
b100 %
0!
1#
#13000
b100 &
1!
0#
#13250
b101 %
0!
1#
#13500
b101 &
1!
0#
#13750
b110 %
0!
1#
#14000
b110 &
1!
0#
#14250
b111 %
0!
1#
#14500
b111 &
1!
0#
#14750
b1000 %
0!
1#
#15000
b0 &
0'
0!
0#
#15250
b1001 %
1#
#15500
0#
#15750
1"
b0 %
1#
#16000
1!
0"
1'
0#
#16250
0"
b1 %
0!
1#
#16500
b1 &
1!
0#
#16750
b10 %
0!
1#
#17000
b10 &
1!
0#
#17250
b11 %
0!
1#
#17500
b11 &
1!
0#
#17750
b100 %
0!
1#
#18000
b100 &
1!
0#
#18250
b101 %
0!
1#
#18500
b101 &
1!
0#
#18750
b110 %
0!
1#
#19000
b110 &
1!
0#
#19250
b111 %
0!
1#
#19500
b111 &
1!
0#
#19750
b1000 %
0!
1#
#20000
b0 &
0'
0!
0#
#20250
b1001 %
1#
#20500
0#
#20750
1"
b0 %
1#
#21000
1!
0"
1'
0#
#21250
0"
b1 %
0!
1#
#21500
b1 &
1!
0#
#21750
b10 %
0!
1#
#22000
b10 &
1!
0#
#22250
b11 %
0!
1#
#22500
b11 &
1!
0#
#22750
b100 %
0!
1#
#23000
b100 &
1!
0#
#23250
b101 %
0!
1#
#23500
b101 &
1!
0#
#23750
b110 %
0!
1#
#24000
b110 &
1!
0#
#24250
b111 %
0!
1#
#24500
b111 &
1!
0#
#24750
b1000 %
0!
1#
#25000
b0 &
0'
0!
0#
#25250
b1001 %
1#
#25500
0#
#25750
1"
b0 %
1#
#26000
1!
0"
1'
0#
#26250
0"
b1 %
0!
1#
#26500
b1 &
1!
0#
#26750
b10 %
0!
1#
#27000
b10 &
1!
0#
#27250
b11 %
0!
1#
#27500
b11 &
1!
0#
#27750
b100 %
0!
1#
#28000
b100 &
1!
0#
#28250
b101 %
0!
1#
#28500
b101 &
1!
0#
#28750
b110 %
0!
1#
#29000
b110 &
1!
0#
#29250
b111 %
0!
1#
#29500
b111 &
1!
0#
#29750
b1000 %
0!
1#
#30000
b0 &
0'
0!
0#
#30250
b1001 %
1#
#30500
0#
#30750
1"
b0 %
1#
#31000
1!
0"
1'
0#
#31250
0"
b1 %
0!
1#
#31500
b1 &
1!
0#
#31750
b10 %
0!
1#
#32000
b10 &
1!
0#
#32250
b11 %
0!
1#
#32500
b11 &
1!
0#
#32750
b100 %
0!
1#
#33000
b100 &
1!
0#
#33250
b101 %
0!
1#
#33500
b101 &
1!
0#
#33750
b110 %
0!
1#
#34000
b110 &
1!
0#
#34250
b111 %
0!
1#
#34500
b111 &
1!
0#
#34750
b1000 %
0!
1#
#35000
b0 &
0'
0!
0#
#35250
b1001 %
1#
#35500
0#
#35750
1"
b0 %
1#
#36000
1!
0"
1'
0#
#36250
0"
b1 %
0!
1#
#36500
b1 &
1!
0#
#36750
b10 %
0!
1#
#37000
b10 &
1!
0#
#37250
b11 %
0!
1#
#37500
b11 &
1!
0#
#37750
b100 %
0!
1#
#38000
b100 &
1!
0#
#38250
b101 %
0!
1#
#38500
b101 &
1!
0#
#38750
b110 %
0!
1#
#39000
b110 &
1!
0#
#39250
b111 %
0!
1#
#39500
b111 &
1!
0#
#39750
b1000 %
0!
1#
#40000
b0 &
0'
0!
0#
#40250
b1001 %
1#
#40500
0#
#40750
1"
b0 %
1#
#41000
1!
0"
1'
0#
#41250
0"
b1 %
0!
1#
#41500
b1 &
1!
0#
#41750
b10 %
0!
1#
#42000
b10 &
1!
0#
#42250
b11 %
0!
1#
#42500
b11 &
1!
0#
#42750
b100 %
0!
1#
#43000
b100 &
1!
0#
#43250
b101 %
0!
1#
#43500
b101 &
1!
0#
#43750
b110 %
0!
1#
#44000
b110 &
1!
0#
#44250
b111 %
0!
1#
#44500
b111 &
1!
0#
#44750
b1000 %
0!
1#
#45000
b0 &
0'
0!
0#
#45250
b1001 %
1#
#45500
0#
#45750
1"
b0 %
1#
#46000
1!
0"
1'
0#
#46250
0"
b1 %
0!
1#
#46500
b1 &
1!
0#
#46750
b10 %
0!
1#
#47000
b10 &
1!
0#
#47250
b11 %
0!
1#
#47500
b11 &
1!
0#
#47750
b100 %
0!
1#
#48000
b100 &
1!
0#
#48250
b101 %
0!
1#
#48500
b101 &
1!
0#
#48750
b110 %
0!
1#
#49000
b110 &
1!
0#
#49250
b111 %
0!
1#
#49500
b111 &
1!
0#
#49750
b1000 %
0!
1#
#50000
b0 &
0'
0!
0#
#50250
b1001 %
1#
#50500
0#
#50750
1"
b0 %
1#
#51000
1!
0"
1'
0#
#51250
0"
b1 %
0!
1#
#51500
b1 &
1!
0#
#51750
b10 %
0!
1#
#52000
b10 &
1!
0#
#52250
b11 %
0!
1#
#52500
b11 &
1!
0#
#52750
b100 %
0!
1#
#53000
b100 &
1!
0#
#53250
b101 %
0!
1#
#53500
b101 &
1!
0#
#53750
b110 %
0!
1#
#54000
b110 &
1!
0#
#54250
b111 %
0!
1#
#54500
b111 &
1!
0#
#54750
b1000 %
0!
1#
#55000
b0 &
0'
0!
0#
#55250
b1001 %
1#
#55500
0#
#55750
1"
b0 %
1#
#56000
1!
0"
1'
0#
#56250
0"
b1 %
0!
1#
#56500
b1 &
1!
0#
#56750
b10 %
0!
1#
#57000
b10 &
1!
0#
#57250
b11 %
0!
1#
#57500
b11 &
1!
0#
#57750
b100 %
0!
1#
#58000
b100 &
1!
0#
#58250
b101 %
0!
1#
#58500
b101 &
1!
0#
#58750
b110 %
0!
1#
#59000
b110 &
1!
0#
#59250
b111 %
0!
1#
#59500
b111 &
1!
0#
#59750
b1000 %
0!
1#
#60000
b0 &
0'
0!
0#
#60250
b1001 %
1#
#60500
0#
#60750
1"
b0 %
1#
#61000
1!
0"
1'
0#
#61250
0"
b1 %
0!
1#
#61500
b1 &
1!
0#
#61750
b10 %
0!
1#
#62000
b10 &
1!
0#
#62250
b11 %
0!
1#
#62500
b11 &
1!
0#
#62750
b100 %
0!
1#
#63000
b100 &
1!
0#
#63250
b101 %
0!
1#
#63500
b101 &
1!
0#
#63750
b110 %
0!
1#
#64000
b110 &
1!
0#
#64250
b111 %
0!
1#
#64500
b111 &
1!
0#
#64750
b1000 %
0!
1#
#65000
b0 &
0'
0!
0#
#65250
b1001 %
1#
#65500
0#
#65750
1"
b0 %
1#
#66000
1!
0"
1'
0#
#66250
0"
b1 %
0!
1#
#66500
b1 &
1!
0#
#66750
b10 %
0!
1#
#67000
b10 &
1!
0#
#67250
b11 %
0!
1#
#67500
b11 &
1!
0#
#67750
b100 %
0!
1#
#68000
b100 &
1!
0#
#68250
b101 %
0!
1#
#68500
b101 &
1!
0#
#68750
b110 %
0!
1#
#69000
b110 &
1!
0#
#69250
b111 %
0!
1#
#69500
b111 &
1!
0#
#69750
b1000 %
0!
1#
#70000
b0 &
0'
0!
0#
#70250
b1001 %
1#
#70500
0#
#70750
1"
b0 %
1#
#71000
1!
0"
1'
0#
#71250
0"
b1 %
0!
1#
#71500
b1 &
1!
0#
#71750
b10 %
0!
1#
#72000
b10 &
1!
0#
#72250
b11 %
0!
1#
#72500
b11 &
1!
0#
#72750
b100 %
0!
1#
#73000
b100 &
1!
0#
#73250
b101 %
0!
1#
#73500
b101 &
1!
0#
#73750
b110 %
0!
1#
#74000
b110 &
1!
0#
#74250
b111 %
0!
1#
#74500
b111 &
1!
0#
#74750
b1000 %
0!
1#
#75000
b0 &
0'
0!
0#
#75250
b1001 %
1#
#75500
0#
#75750
1"
b0 %
1#
#76000
1!
0"
1'
0#
#76250
0"
b1 %
0!
1#
#76500
b1 &
1!
0#
#76750
b10 %
0!
1#
#77000
b10 &
1!
0#
#77250
b11 %
0!
1#
#77500
b11 &
1!
0#
#77750
b100 %
0!
1#
#78000
b100 &
1!
0#
#78250
b101 %
0!
1#
#78500
b101 &
1!
0#
#78750
b110 %
0!
1#
#79000
b110 &
1!
0#
#79250
b111 %
0!
1#
#79500
b111 &
1!
0#
#79750
b1000 %
0!
1#
#80000
b0 &
0'
0!
0#
#80250
b1001 %
1#
#80500
0#
#80750
1"
b0 %
1#
#81000
1!
0"
1'
0#
#81250
0"
b1 %
0!
1#
#81500
b1 &
1!
0#
#81750
b10 %
0!
1#
#82000
b10 &
1!
0#
#82250
b11 %
0!
1#
#82500
b11 &
1!
0#
#82750
b100 %
0!
1#
#83000
b100 &
1!
0#
#83250
b101 %
0!
1#
#83500
b101 &
1!
0#
#83750
b110 %
0!
1#
#84000
b110 &
1!
0#
#84250
b111 %
0!
1#
#84500
b111 &
1!
0#
#84750
b1000 %
0!
1#
#85000
b0 &
0'
0!
0#
#85250
b1001 %
1#
#85500
0#
#85750
1"
b0 %
1#
#86000
1!
0"
1'
0#
#86250
0"
b1 %
0!
1#
#86500
b1 &
1!
0#
#86750
b10 %
0!
1#
#87000
b10 &
1!
0#
#87250
b11 %
0!
1#
#87500
b11 &
1!
0#
#87750
b100 %
0!
1#
#88000
b100 &
1!
0#
#88250
b101 %
0!
1#
#88500
b101 &
1!
0#
#88750
b110 %
0!
1#
#89000
b110 &
1!
0#
#89250
b111 %
0!
1#
#89500
b111 &
1!
0#
#89750
b1000 %
0!
1#
#90000
b0 &
0'
0!
0#
#90250
b1001 %
1#
#90500
0#
#90750
1"
b0 %
1#
#91000
1!
0"
1'
0#
#91250
0"
b1 %
0!
1#
#91500
b1 &
1!
0#
#91750
b10 %
0!
1#
#92000
b10 &
1!
0#
#92250
b11 %
0!
1#
#92500
b11 &
1!
0#
#92750
b100 %
0!
1#
#93000
b100 &
1!
0#
#93250
b101 %
0!
1#
#93500
b101 &
1!
0#
#93750
b110 %
0!
1#
#94000
b110 &
1!
0#
#94250
b111 %
0!
1#
#94500
b111 &
1!
0#
#94750
b1000 %
0!
1#
#95000
b0 &
0'
0!
0#
#95250
b1001 %
1#
#95500
0#
#95750
1"
b0 %
1#
#96000
1!
0"
1'
0#
#96250
0"
b1 %
0!
1#
#96500
b1 &
1!
0#
#96750
b10 %
0!
1#
#97000
b10 &
1!
0#
#97250
b11 %
0!
1#
#97500
b11 &
1!
0#
#97750
b100 %
0!
1#
#98000
b100 &
1!
0#
#98250
b101 %
0!
1#
#98500
b101 &
1!
0#
#98750
b110 %
0!
1#
#99000
b110 &
1!
0#
#99250
b111 %
0!
1#
#99500
b111 &
1!
0#
#99750
b1000 %
0!
1#
#100000
b0 &
0'
0!
0#
#100250
b1001 %
1#
#100500
0#
#100750
1"
b0 %
1#
